upload_tm_records.py
upload_tm_records-1.0.1.dist-info/licenses/AUTHORS
upload_tm_records-1.0.1.dist-info/licenses/LICENSE.txt
upload_tm_records-1.0.1.dist-info/METADATA
upload_tm_records-1.0.1.dist-info/WHEEL
upload_tm_records-1.0.1.dist-info/entry_points.txt
upload_tm_records-1.0.1.dist-info/top_level.txt
upload_tm_records-1.0.1.dist-info/RECORD
